nemcore/__init__.py
nemcore/api.py
nemcore/cache.py
nemcore/const.py
nemcore/encrypt.py
nemcore/exceptions.py
nemcore/types/__init__.py
nemcore/types/easy_access.py
nemcore/types/fm_like_resp.py
nemcore/types/fm_trash_resp.py
nemcore/types/get_album_info_resp.py
nemcore/types/get_artist_albums_resp.py
nemcore/types/get_artist_info_resp.py
nemcore/types/get_dj_channels_resp.py
nemcore/types/get_dj_programs_resp.py
nemcore/types/get_personal_fm_resp.py
nemcore/types/get_playlist_detail_resp.py
nemcore/types/get_recommend_resource_resp.py
nemcore/types/get_recommend_songs_resp.py
nemcore/types/get_song_comments_resp.py
nemcore/types/get_song_detail_resp.py
nemcore/types/get_song_lyric_resp.py
nemcore/types/get_song_url_resp.py
nemcore/types/get_top_artists_resp.py
nemcore/types/get_top_playlists_resp.py
nemcore/types/get_user_account_resp.py
nemcore/types/get_user_playlist_resp.py
nemcore/types/login_resp.py
nemcore/types/new_album_resp.py
nemcore/types/playlist.py
nemcore/types/search_resp.py
nemcore/types/user_profile.py
nemcore/utils.py
nemcore-0.1.8.dist-info/LICENSE
nemcore-0.1.8.dist-info/WHEEL
nemcore-0.1.8.dist-info/METADATA
nemcore-0.1.8.dist-info/RECORD
