Metadata-Version: 2.1
Name: nemcore
Version: 0.1.8
Summary: NetEase Cloud Music api client
Home-page: https://github.com/nnnewb/nemcore
License: MIT
Author: weak_ptr
Author-email: weak_ptr@outlook.com
Requires-Python: >=3.6,<4.0
Classifier: Development Status :: 2 - Pre-Alpha
Classifier: License :: OSI Approved :: MIT License
Classifier: Natural Language :: Chinese (Simplified)
Classifier: Programming Language :: Python :: 3
Classifier: Programming Language :: Python :: 3 :: Only
Classifier: Programming Language :: Python :: 3.6
Classifier: Programming Language :: Python :: 3.7
Classifier: Programming Language :: Python :: 3.8
Classifier: Programming Language :: Python :: 3.9
Classifier: Typing :: Typed
Requires-Dist: cachetools (>=4.0,<5.0)
Requires-Dist: importlib-metadata (>=3.3.0,<4.0.0)
Requires-Dist: pycryptodomex (>=3.9,<4.0)
Requires-Dist: requests (>=2.22.0,<3.0.0)
Project-URL: Documentation, https://nemcore.readthedocs.io/en/latest/
Project-URL: Repository, https://github.com/nnnewb/nemcore
